CHANGES.md
MANIFEST.in
README.md
VERSION.txt
pyproject.toml
setup.py
ept/__init__.py
ept/data.py
ept/endpoint.py
ept/ept.py
ept/hierarchy.py
ept/info.py
ept/laz.py
ept/metadata.py
ept/pool.py
ept/schema.py
ept_python.egg-info/PKG-INFO
ept_python.egg-info/SOURCES.txt
ept_python.egg-info/dependency_links.txt
ept_python.egg-info/requires.txt
ept_python.egg-info/top_level.txt
test/test_endpoint.py
test/test_ept.py
test/test_hierarchy.py
test/ept-star/ept-data/0-0-0-0.laz
test/ept-star/ept-data/1-0-0-0.laz
test/ept-star/ept-data/1-0-0-1.laz
test/ept-star/ept-data/1-0-1-0.laz
test/ept-star/ept-data/1-1-0-0.laz
test/ept-star/ept-data/1-1-0-1.laz
test/ept-star/ept-data/1-1-1-0.laz
test/ept-star/ept-data/1-1-1-1.laz
test/ept-star/ept-data/2-0-0-1.laz
test/ept-star/ept-data/2-0-1-1.laz
test/ept-star/ept-data/2-1-0-1.laz
test/ept-star/ept-data/2-1-1-1.laz
test/ept-star/ept-data/2-1-2-1.laz
test/ept-star/ept-data/2-1-3-1.laz
test/ept-star/ept-data/2-2-0-1.laz
test/ept-star/ept-data/2-2-1-1.laz
test/ept-star/ept-data/2-2-1-2.laz
test/ept-star/ept-data/2-2-2-1.laz
test/ept-star/ept-data/2-2-2-2.laz
test/ept-star/ept-data/2-2-3-1.laz
test/ept-star/ept-data/2-3-0-1.laz
test/ept-star/ept-data/2-3-1-1.laz
test/ept-star/ept-data/2-3-1-2.laz
test/ept-star/ept-data/2-3-2-1.laz
test/ept-star/ept-data/2-3-2-2.laz
test/ept-star/ept-data/2-3-3-1.laz
test/ept-star/ept-data/2-3-3-2.laz
test/ept-star/ept-data/3-4-2-2.laz
test/ept-star/ept-data/3-4-3-2.laz
test/ept-star/ept-data/3-4-3-3.laz
test/ept-star/ept-data/3-4-4-2.laz
test/ept-star/ept-data/3-4-4-3.laz
test/ept-star/ept-data/3-4-4-4.laz
test/ept-star/ept-data/3-4-4-5.laz
test/ept-star/ept-data/3-4-5-2.laz
test/ept-star/ept-data/3-4-5-3.laz
test/ept-star/ept-data/3-4-5-4.laz
test/ept-star/ept-data/3-4-6-2.laz
test/ept-star/ept-data/3-4-6-3.laz
test/ept-star/ept-data/3-4-7-2.laz
test/ept-star/ept-data/3-4-7-3.laz
test/ept-star/ept-data/3-5-2-2.laz
test/ept-star/ept-data/3-5-3-2.laz
test/ept-star/ept-data/3-5-3-3.laz
test/ept-star/ept-data/3-5-4-2.laz
test/ept-star/ept-data/3-5-4-3.laz
test/ept-star/ept-data/3-5-4-4.laz
test/ept-star/ept-data/3-5-4-5.laz
test/ept-star/ept-data/3-5-5-2.laz
