Metadata-Version: 2.1
Name: ept-python
Version: 0.6
Summary: UNKNOWN
Home-page: https://github.com/hobu/ept-python
Author: Howard Butler
Author-email: howard@hobu.co
Maintainer: Howard Butler
Maintainer-email: howard@hobu.co
License: BSD
Keywords: point cloud data organization
Platform: UNKNOWN
Classifier: Development Status :: 4 - Beta
Classifier: Intended Audience :: Developers
Classifier: Intended Audience :: Science/Research
Classifier: License :: OSI Approved :: BSD License
Classifier: Operating System :: OS Independent
Classifier: Programming Language :: Python :: 2.7
Classifier: Programming Language :: Python :: 3
Classifier: Topic :: Scientific/Engineering :: GIS
Provides-Extra: s3
